surfalize/__init__.py
surfalize/_version.py
surfalize/abbottfirestone.py
surfalize/autocorrelation.py
surfalize/batch.py
surfalize/cache.py
surfalize/cli.py
surfalize/examples.py
surfalize/exceptions.py
surfalize/filter.py
surfalize/image.py
surfalize/mathutils.py
surfalize/plotting.py
surfalize/profile.py
surfalize/surface.py
surfalize/utils.py
surfalize/file/__init__.py
surfalize/file/al3d.py
surfalize/file/cag.py
surfalize/file/common.py
surfalize/file/dat.py
surfalize/file/fits.py
surfalize/file/gwy.py
surfalize/file/nms.py
surfalize/file/opd.py
surfalize/file/os3d.py
surfalize/file/plu.py
surfalize/file/plux.py
surfalize/file/sdf.py
surfalize/file/sflz.py
surfalize/file/sur.py
surfalize/file/tmd.py
surfalize/file/vk.py
surfalize/file/x3p.py
surfalize/file/xyz.py
surfalize/file/zmg.py
surfalize-0.16.6.dist-info/licenses/LICENSE
surfalize-0.16.6.dist-info/METADATA
surfalize-0.16.6.dist-info/WHEEL
surfalize-0.16.6.dist-info/entry_points.txt
surfalize-0.16.6.dist-info/top_level.txt
surfalize-0.16.6.dist-info/RECORD
