Metadata-Version: 2.4
Name: surfalize
Version: 0.16.6
Summary: A python module to analyze surface roughness
Author-email: Frederic Schell <frederic.schell@iws.fraunhofer.de>
License:                     GNU GENERAL PUBLIC LICENSE
Classifier: Programming Language :: Python
Classifier: Programming Language :: Python :: 3
Classifier: Programming Language :: Python :: 3.9
Classifier: Programming Language :: Python :: 3.10
Classifier: Programming Language :: Python :: 3.11
Classifier: Programming Language :: Python :: 3.12
Classifier: Programming Language :: Python :: 3.13
Requires-Python: >=3.9
License-File: LICENSE
Requires-Dist: numpy>=1.18.1
Requires-Dist: matplotlib>=3.1.1
Requires-Dist: pandas>=1.0.1
Requires-Dist: scipy>=1.4.1
Requires-Dist: tqdm>=4.64.1
Requires-Dist: openpyxl>=3.1.2
Requires-Dist: scikit-learn
Requires-Dist: python-dateutil
Requires-Dist: pillow
Requires-Dist: chardet
Provides-Extra: 3d
Requires-Dist: pyvista; extra == "3d"
Requires-Dist: trame; extra == "3d"
Requires-Dist: trame-vtk; extra == "3d"
Requires-Dist: trame-vuetify; extra == "3d"
Requires-Dist: trame-components; extra == "3d"
Provides-Extra: doc
Requires-Dist: sphinx; extra == "doc"
Requires-Dist: numpydoc; extra == "doc"
Requires-Dist: furo; extra == "doc"
Provides-Extra: tests
Requires-Dist: pytest; extra == "tests"
Provides-Extra: cli
Requires-Dist: click; extra == "cli"
Requires-Dist: fpdf2; extra == "cli"
Provides-Extra: all
Requires-Dist: pyvista; extra == "all"
Requires-Dist: trame; extra == "all"
Requires-Dist: trame-vtk; extra == "all"
Requires-Dist: trame-vuetify; extra == "all"
Requires-Dist: trame-components; extra == "all"
Requires-Dist: sphinx; extra == "all"
Requires-Dist: furo; extra == "all"
Requires-Dist: numpydoc; extra == "all"
Requires-Dist: pytest; extra == "all"
Requires-Dist: click; extra == "all"
Requires-Dist: fpdf2; extra == "all"
Dynamic: license-file
